setup.py
webrpc.py
webrpc.egg-info/PKG-INFO
webrpc.egg-info/SOURCES.txt
webrpc.egg-info/dependency_links.txt
webrpc.egg-info/requires.txt
webrpc.egg-info/top_level.txt