Metadata-Version: 1.0
Name: webrpc
Version: 0.0.5
Summary: wep rpc framework.
Home-page: http://github.com/kulasama/webrpc
Author: kula
Author-email: kulasama@gmail.com
License: MIT
Platform: any
